telegrambots/__init__.py
telegrambots/py.typed
telegrambots/custom/__init__.py
telegrambots/custom/client.py
telegrambots/custom/dispatcher.py
telegrambots/custom/general.py
telegrambots/custom/contexts/__init__.py
telegrambots/custom/contexts/_contexts/__init__.py
telegrambots/custom/contexts/_contexts/_continuously_handler.py
telegrambots/custom/contexts/_contexts/callback_query_context.py
telegrambots/custom/contexts/_contexts/context_template.py
telegrambots/custom/contexts/_contexts/message_context.py
telegrambots/custom/exceptions/__init__.py
telegrambots/custom/exceptions/handlers.py
telegrambots/custom/exceptions/propagations.py
telegrambots/custom/extensions/__init__.py
telegrambots/custom/extensions/context.py
telegrambots/custom/extensions/dispatcher.py
telegrambots/custom/filters/__init__.py
telegrambots/custom/filters/callback_query.py
telegrambots/custom/filters/messages.py
telegrambots/custom/filters/_filters/__init__.py
telegrambots/custom/filters/_filters/filter_template.py
telegrambots/custom/filters/_filters/message_filters.py
telegrambots/custom/handlers/__init__.py
telegrambots/custom/handlers/_handlers/__init__.py
telegrambots/custom/handlers/_handlers/abstracts.py
telegrambots/custom/handlers/_handlers/handler_template.py
telegrambots/custom/handlers/_handlers/update_handler.py
telegrambots/custom/handlers/exceptions/__init__.py
telegrambots/custom/handlers/exceptions/exception_handler.py
telegrambots/custom/helpers/__init__.py
telegrambots/custom/helpers/buttons.py
telegrambots/custom/key_resolvers/__init__.py
telegrambots/custom/key_resolvers/custom_resolvers.py
telegrambots/custom/key_resolvers/key_builder.py
telegrambots/custom/key_resolvers/key_resolver.py
telegrambots/custom/processor/__init__.py
telegrambots/custom/processor/_processor/__init__.py
telegrambots/custom/processor/_processor/parallel_processor.py
telegrambots/custom/processor/_processor/processor_template.py
telegrambots/custom/processor/_processor/sequential_processor.py
telegrambots_custom-0.0.7rc3.dist-info/LICENSE
telegrambots_custom-0.0.7rc3.dist-info/METADATA
telegrambots_custom-0.0.7rc3.dist-info/WHEEL
telegrambots_custom-0.0.7rc3.dist-info/top_level.txt
telegrambots_custom-0.0.7rc3.dist-info/RECORD
