Metadata-Version: 2.1
Name: telegrambots-custom
Version: 0.0.7rc3
Summary: A custom extension packages for telegrambots.
Home-page: https://github.com/python-telegrambots/custom-telegrambots
Author: immmdreza
Author-email: ir310022@gmail.com
Project-URL: Bug Tracker, https://github.com/python-telegrambots/custom-telegrambots/issues
Classifier: Programming Language :: Python :: 3
Classifier: License :: OSI Approved :: MIT License
Classifier: Operating System :: OS Independent
Requires-Python: >=3.10
License-File: LICENSE
Requires-Dist: aiohttp (==3.8.1)
Requires-Dist: telegrambots (==0.0.13rc0)
